wp_dso_publish/__init__.py
wp_dso_publish/app_gui.py
wp_dso_publish/local_settings.py
wp_dso_publish/safe_helper.py
wp_dso_publish/saved-settings.py
wp_dso_publish/style.css
wp_dso_publish-0.30.data/scripts/wp-dso-publish.py
wp_dso_publish-0.30.dist-info/METADATA
wp_dso_publish-0.30.dist-info/WHEEL
wp_dso_publish-0.30.dist-info/top_level.txt
wp_dso_publish-0.30.dist-info/RECORD
