Metadata-Version: 2.1
Name: wp-dso-publish
Version: 0.30
Summary: Utility to push SAFE policies for a specific dataset.
Home-page: https://github.com/RENCI-NRIG/impact-utils/tree/master/wp_dso_publish
Author: ibaldin
Author-email: ibaldin@renci.org
License: MIT
Platform: UNKNOWN
Classifier: Programming Language :: Python :: 3
Classifier: License :: OSI Approved :: MIT License
Classifier: Operating System :: OS Independent
Requires-Dist: PyForms-GUI (==5)
Requires-Dist: pycryptodome (==3.8.2)
Requires-Dist: requests (==2.22.0)
